LICENSE
MANIFEST.in
README.md
setup.py
Uses-Cases/__init__.py
asposepdfcloud/__init__.py
asposepdfcloud/api_client.py
asposepdfcloud/configuration.py
asposepdfcloud/rest.py
asposepdfcloud.egg-info/PKG-INFO
asposepdfcloud.egg-info/SOURCES.txt
asposepdfcloud.egg-info/dependency_links.txt
asposepdfcloud.egg-info/requires.txt
asposepdfcloud.egg-info/top_level.txt
asposepdfcloud/apis/__init__.py
asposepdfcloud/apis/pdf_api.py
asposepdfcloud/models/__init__.py
asposepdfcloud/models/annotation.py
asposepdfcloud/models/annotation_flags.py
asposepdfcloud/models/annotation_info.py
asposepdfcloud/models/annotation_state.py
asposepdfcloud/models/annotation_type.py
asposepdfcloud/models/annotations_info.py
asposepdfcloud/models/annotations_info_response.py
asposepdfcloud/models/antialiasing_processing_type.py
asposepdfcloud/models/aspose_response.py
asposepdfcloud/models/attachment.py
asposepdfcloud/models/attachment_info.py
asposepdfcloud/models/attachment_response.py
asposepdfcloud/models/attachments.py
asposepdfcloud/models/attachments_response.py
asposepdfcloud/models/bookmark.py
asposepdfcloud/models/bookmark_response.py
asposepdfcloud/models/bookmarks.py
asposepdfcloud/models/bookmarks_response.py
asposepdfcloud/models/border.py
asposepdfcloud/models/border_corner_style.py
asposepdfcloud/models/border_effect.py
asposepdfcloud/models/border_info.py
asposepdfcloud/models/border_style.py
asposepdfcloud/models/box_style.py
asposepdfcloud/models/cap_style.py
asposepdfcloud/models/caption_position.py
asposepdfcloud/models/caret_annotation.py
asposepdfcloud/models/caret_annotation_response.py
asposepdfcloud/models/caret_annotations.py
asposepdfcloud/models/caret_annotations_response.py
asposepdfcloud/models/caret_symbol.py
asposepdfcloud/models/cell.py
asposepdfcloud/models/cell_recognized.py
asposepdfcloud/models/check_box_field.py
asposepdfcloud/models/check_box_field_response.py
asposepdfcloud/models/check_box_fields.py
asposepdfcloud/models/check_box_fields_response.py
asposepdfcloud/models/choice_field.py
asposepdfcloud/models/circle_annotation.py
asposepdfcloud/models/circle_annotation_response.py
asposepdfcloud/models/circle_annotations.py
