Metadata-Version: 2.4
Name: asposepdfcloud
Version: 25.11.0
Summary: Aspose.PDF Cloud
Home-page: https://products.aspose.cloud/pdf/cloud
Author: Aspose PDF Cloud
Author-email: 
License: MIT
Project-URL: Source With Tests, https://github.com/aspose-pdf-cloud/aspose-pdf-cloud-python
Project-URL: Website, https://www.aspose.cloud
Project-URL: Product Home, https://products.aspose.cloud/pdf/cloud
Project-URL: Documentation, https://docs.aspose.cloud/display/pdfcloud/Home
Project-URL: Free Support Forum, https://forum.aspose.cloud/c/pdf
Project-URL: Paid Support Helpdesk, https://helpdesk.aspose.cloud/
Project-URL: Blog, https://blog.aspose.cloud/category/aspose-products/aspose-pdf-product-family/
Keywords: Aspose,Cloud,PDF,Aspose.PDF,Aspose.PDF-Cloud,Aspose.Total-Cloud,REST,API,EPUB,HTML,TEX,MHT,PCL,PS,PostScript,SVG,XML,XPS,XSLFO,MD,Markdown,XLS,XLSX,PPTX,DOC,DOCX,EPUB,HTML,MobiXML,SVG,JPEG,EMF,PNG,BMP,GIF,TIFF,XML,XPS,Text,FDF,XFDF,PDFA3,PDF-to-DOC,PDF-to-DOCX,PDF-to-HTML,PDF-to-PDFA,PDF-to-TIFF,PDF-to-SVG,PDF-to-EPUB,PDF-to-PPTX,PDF-to-TEX,PDF-to-MobiXML,PDF-to-XFA,PDF-to-XML,PDF-to-XPS,PDF-to-XLS,EPUB-to-PDF,Web-to-PDF,TEX-to-PDF,MHT-to-PDF,HTML-to-PDF,PS-to-PDF,PostScript-to-PDF,XSI
Classifier: Development Status :: 5 - Production/Stable
Classifier: Intended Audience :: Developers
Classifier: Topic :: Software Development
Classifier: License :: OSI Approved :: MIT License
Classifier: Programming Language :: Python :: 2
Classifier: Programming Language :: Python :: 3
License-File: LICENSE
Requires-Dist: urllib3>=1.15
Requires-Dist: six>=1.10
Requires-Dist: certifi>=14.05.14
Requires-Dist: python-dateutil>=2.5.3
Requires-Dist: setuptools>=21.0.0
Provides-Extra: test
Requires-Dist: requests>=2.18.4; extra == "test"
Requires-Dist: coverage>=4.0.3; extra == "test"
Requires-Dist: nose>=1.3.7; extra == "test"
Requires-Dist: pluggy>=0.3.1; extra == "test"
Requires-Dist: py>=1.4.31; extra == "test"
Requires-Dist: randomize>=0.13; extra == "test"
Dynamic: author
Dynamic: classifier
Dynamic: description
Dynamic: description-content-type
Dynamic: home-page
Dynamic: keywords
Dynamic: license
Dynamic: license-file
Dynamic: project-url
Dynamic: provides-extra
Dynamic: requires-dist
Dynamic: summary
